pack/__init__.py
aws_works-0.0.6.dist-info/LICENSE
aws_works-0.0.6.dist-info/METADATA
aws_works-0.0.6.dist-info/WHEEL
aws_works-0.0.6.dist-info/top_level.txt
aws_works-0.0.6.dist-info/RECORD
